circuitpython_displayio_effects-2.0.0.dist-info/licenses/LICENSE
displayio_effects/__init__.py
displayio_effects/colorwheel_effect.py
displayio_effects/fluctuation_effect.py
circuitpython_displayio_effects-2.0.0.dist-info/METADATA
circuitpython_displayio_effects-2.0.0.dist-info/WHEEL
circuitpython_displayio_effects-2.0.0.dist-info/top_level.txt
circuitpython_displayio_effects-2.0.0.dist-info/RECORD
