Metadata-Version: 2.4
Name: circuitpython-displayio-effects
Version: 2.0.0
Summary: Add some flair to your displayio widgets with effects!
Author: circuitpython
License: MIT
Project-URL: Homepage, https://github.com/circuitpython/CircuitPython_Org_DisplayIO_Effects
Keywords: adafruit,blinka,circuitpython,micropython,displayio_effects,effects,,displayio,,widget
Classifier: Intended Audience :: Developers
Classifier: Topic :: Software Development :: Libraries
Classifier: Topic :: Software Development :: Embedded Systems
Classifier: Topic :: System :: Hardware
Classifier: License :: OSI Approved :: MIT License
Classifier: Programming Language :: Python :: 3
License-File: LICENSE
Requires-Dist: Adafruit-Blinka
Requires-Dist: adafruit-circuitpython-itertools
Provides-Extra: optional
Dynamic: license-file
